sos_javascript/__init__.py
sos_javascript/_version.py
sos_javascript/kernel.py
sos_javascript-0.20.0.dist-info/METADATA
sos_javascript-0.20.0.dist-info/WHEEL
sos_javascript-0.20.0.dist-info/entry_points.txt
sos_javascript-0.20.0.dist-info/top_level.txt
sos_javascript-0.20.0.dist-info/RECORD
