Metadata-Version: 2.1
Name: sos-javascript
Version: 0.20.0
Summary: SoS Notebook extension for JavaScript
Home-page: https://github.com/vatlab/SOS
Author: Bo Peng
Author-email: bpeng@mdanderson.org
Maintainer: Bo Peng
Maintainer-email: bpeng@mdanderson.org
License: 3-clause BSD
Platform: UNKNOWN
Classifier: Development Status :: 4 - Beta
Classifier: Environment :: Console
Classifier: License :: OSI Approved :: BSD License
Classifier: Natural Language :: English
Classifier: Operating System :: POSIX :: Linux
Classifier: Operating System :: MacOS :: MacOS X
Classifier: Operating System :: Microsoft :: Windows
Classifier: Intended Audience :: Information Technology
Classifier: Intended Audience :: Science/Research
Classifier: Programming Language :: Python :: 3 :: Only
Classifier: Programming Language :: Python :: Implementation :: CPython
Requires-Dist: sos (>=0.18.0)
Requires-Dist: sos-notebook (>=0.18.0)
